{"properties": [
  {
    "name": "application.version",
    "type": "java.lang.String",
    "description": "Current application version according to pom.xml"
  },
  {
    "name": "file.resume-filepath",
    "type": "java.lang.String",
    "description": "File path to the resume file"
  },
  {
    "name": "contact.email",
    "type": "java.lang.String",
    "description": "Mail to address for contact form submissions"
  },
  {
    "name": "contact.url",
    "type": "java.lang.String",
    "description": "The URL of the platform from which the contact form is submitted"
  },
  {
    "name": "settings.cors_origins",
    "type": "java.lang.String",
    "description": "Comma-separated list of allowed CORS origins (e.g. https://example.com,https://www.example.com)"
  },
  {
    "name": "friendlycaptcha.api-key",
    "type": "java.lang.String",
    "description": "An API Key to prove the application has the rights to check response from Captcha server."
  },
  {
    "name": "friendlycaptcha.site-key",
    "type": "java.lang.String",
    "description": "The website key for the Captcha server."
  }
]}